ovos_skill_diagnostics/LICENSE
ovos_skill_diagnostics/MANIFEST.in
ovos_skill_diagnostics/README.md
ovos_skill_diagnostics/__init__.py
ovos_skill_diagnostics/requirements.txt
ovos_skill_diagnostics/version.py
ovos_skill_diagnostics/locale/ca/available_memory.dialog
ovos_skill_diagnostics/locale/ca/cpu_percent.dialog
ovos_skill_diagnostics/locale/ca/current_lang.dialog
ovos_skill_diagnostics/locale/ca/current_memory.dialog
ovos_skill_diagnostics/locale/ca/has_gpu.dialog
ovos_skill_diagnostics/locale/ca/kernel_version.dialog
ovos_skill_diagnostics/locale/ca/no_gpu.dialog
ovos_skill_diagnostics/locale/ca/no_secondary_langs.dialog
ovos_skill_diagnostics/locale/ca/primary_lang.dialog
ovos_skill_diagnostics/locale/ca/query_cpu_usage.intent
ovos_skill_diagnostics/locale/ca/query_extra_langs.intent
ovos_skill_diagnostics/locale/ca/query_gpu.intent
ovos_skill_diagnostics/locale/ca/query_kernel_version.intent
ovos_skill_diagnostics/locale/ca/query_langs.intent
ovos_skill_diagnostics/locale/ca/query_memory_usage.intent
ovos_skill_diagnostics/locale/ca/query_ovos_location.intent
ovos_skill_diagnostics/locale/ca/query_primary_lang.intent
ovos_skill_diagnostics/locale/ca/query_user_lang.intent
ovos_skill_diagnostics/locale/ca/query_user_location.intent
ovos_skill_diagnostics/locale/ca/secondary_langs.dialog
ovos_skill_diagnostics/locale/ca/system_location.dialog
ovos_skill_diagnostics/locale/ca/user_location.dialog
ovos_skill_diagnostics/locale/da/available_memory.dialog
ovos_skill_diagnostics/locale/da/cpu_percent.dialog
ovos_skill_diagnostics/locale/da/current_lang.dialog
ovos_skill_diagnostics/locale/da/current_memory.dialog
ovos_skill_diagnostics/locale/da/has_gpu.dialog
ovos_skill_diagnostics/locale/da/kernel_version.dialog
ovos_skill_diagnostics/locale/da/no_gpu.dialog
ovos_skill_diagnostics/locale/da/no_secondary_langs.dialog
ovos_skill_diagnostics/locale/da/primary_lang.dialog
ovos_skill_diagnostics/locale/da/query_cpu_usage.intent
ovos_skill_diagnostics/ovos_skill_diagnostics.egg-info/PKG-INFO
ovos_skill_diagnostics/ovos_skill_diagnostics.egg-info/SOURCES.txt
ovos_skill_diagnostics/ovos_skill_diagnostics.egg-info/dependency_links.txt
ovos_skill_diagnostics/ovos_skill_diagnostics.egg-info/entry_points.txt
ovos_skill_diagnostics/ovos_skill_diagnostics.egg-info/requires.txt
ovos_skill_diagnostics/ovos_skill_diagnostics.egg-info/top_level.txt
ovos_skill_diagnostics-0.0.8.dist-info/LICENSE
ovos_skill_diagnostics-0.0.8.dist-info/METADATA
ovos_skill_diagnostics-0.0.8.dist-info/WHEEL
ovos_skill_diagnostics-0.0.8.dist-info/entry_points.txt
ovos_skill_diagnostics-0.0.8.dist-info/top_level.txt
ovos_skill_diagnostics-0.0.8.dist-info/RECORD
