Metadata-Version: 2.1
Name: ovos-skill-diagnostics
Version: 0.0.8
Summary: OVOS diagnostics skill
Home-page: https://github.com/OpenVoiceOS/ovos-skill-diagnostics
Author: OpenVoiceOS
Author-email: jarbasai@mailfence.com
License: Apache-2.0
Keywords: ovos skill plugin
License-File: LICENSE
Requires-Dist: ovos-workshop>=0.0.12
Requires-Dist: ovos-lang-parser
Requires-Dist: psutil
